Metadata-Version: 2.1
Name: datalab
Version: 1.2.0
Summary: Google Cloud Datalab
Home-page: https://github.com/googledatalab/pydatalab
Author: Google
Author-email: google-cloud-datalab-feedback@googlegroups.com
License: Apache Software License
Download-URL: https://github.com/googledatalab/pydatalab/archive/v1.1.0.zip
Keywords: Google,GCP,GCS,bigquery
Platform: UNKNOWN
Classifier: Programming Language :: Python
Classifier: Programming Language :: Python :: 2
Classifier: Programming Language :: Python :: 3
Classifier: Development Status :: 4 - Beta
Classifier: Environment :: Other Environment
Classifier: Intended Audience :: Developers
Classifier: License :: OSI Approved :: Apache Software License
Classifier: Operating System :: OS Independent
Classifier: Topic :: Software Development :: Libraries :: Python Modules
Requires-Dist: configparser (>=3.5.0)
Requires-Dist: mock (>=2.0.0)
Requires-Dist: future (>=0.16.0)
Requires-Dist: google-cloud-monitoring (==0.31.1)
Requires-Dist: google-api-core (>=1.10.0)
Requires-Dist: google-api-python-client (>=1.6.2)
Requires-Dist: seaborn (>=0.7.0)
Requires-Dist: plotly (>=1.12.5)
Requires-Dist: httplib2 (>=0.10.3)
Requires-Dist: oauth2client (>=2.2.0)
Requires-Dist: pandas (>=0.22.0)
Requires-Dist: google-auth-httplib2 (>=0.0.2)
Requires-Dist: pandas-profiling (==1.4.0)
Requires-Dist: python-dateutil (>=2.5.0)
Requires-Dist: pytz (>=2015.4)
Requires-Dist: pyyaml (>=3.11)
Requires-Dist: requests (>=2.9.1)
Requires-Dist: scikit-image (>=0.13.0)
Requires-Dist: scikit-learn (>=0.18.2)
Requires-Dist: ipykernel (>=4.5.2)
Requires-Dist: psutil (>=4.3.0)
Requires-Dist: jsonschema (>=2.6.0)
Requires-Dist: six (>=1.10.0)
Requires-Dist: urllib3 (>=1.22)
Requires-Dist: futures (>=3.0.5) ; python_version == "2.7"
